polars_argpartition-0.1.1.dist-info/METADATA
polars_argpartition-0.1.1.dist-info/WHEEL
polars_argpartition/py.typed
polars_argpartition/__init__.py
polars_argpartition/_internal.pyi
polars_argpartition/typing.py
polars_argpartition/README.md
polars_argpartition/_internal.abi3.so
polars_argpartition-0.1.1.dist-info/RECORD
