Metadata-Version: 2.4
Name: polars_argpartition
Version: 0.1.1
Classifier: Programming Language :: Rust
Classifier: Programming Language :: Python :: Implementation :: CPython
Classifier: Programming Language :: Python :: Implementation :: PyPy
Requires-Dist: maturin>=1.8.2
Requires-Dist: polars>=1.8.2
Requires-Python: >=3.8
